jupy_juice/__init__.py
jupy_juice/_modidx.py
jupy_juice/core.py
jupy_juice-0.0.2.dist-info/LICENSE
jupy_juice-0.0.2.dist-info/METADATA
jupy_juice-0.0.2.dist-info/WHEEL
jupy_juice-0.0.2.dist-info/entry_points.txt
jupy_juice-0.0.2.dist-info/top_level.txt
jupy_juice-0.0.2.dist-info/RECORD
