Metadata-Version: 2.1
Name: jupy_juice
Version: 0.0.2
Summary: AI Assistant in Jupyter Notebooks
Home-page: https://github.com/ndendic/jupy-juice
Author: ndendic
Author-email: Nikola Dendic <ndendic@gmail.com>
License: Apache Software License 2.0
Keywords: nbdev jupyter notebook python pydantic-ai pydantic
Classifier: Development Status :: 4 - Beta
Classifier: Intended Audience :: Developers
Classifier: Natural Language :: English
Classifier: Programming Language :: Python :: 3.7
Classifier: Programming Language :: Python :: 3.8
Classifier: Programming Language :: Python :: 3.9
Classifier: Programming Language :: Python :: 3.10
Classifier: Programming Language :: Python :: 3.11
Classifier: Programming Language :: Python :: 3.12
Classifier: License :: OSI Approved :: Apache Software License
Requires-Python: >=3.7
License-File: LICENSE
Requires-Dist: ipynbname>=2024.1.0.0
Requires-Dist: jupyter>=1.1.1
Requires-Dist: pydantic-ai>=0.0.15
Requires-Dist: pydantic-settings>=2.7.1
Requires-Dist: python-dotenv>=1.0.1
Provides-Extra: dev
